crewai_tools/__init__.py
crewai_tools/generate_tool_specs.py
crewai_tools/printer.py
crewai_tools/py.typed
crewai_tools/adapters/__init__.py
crewai_tools/adapters/crewai_rag_adapter.py
crewai_tools/adapters/enterprise_adapter.py
crewai_tools/adapters/lancedb_adapter.py
crewai_tools/adapters/mcp_adapter.py
crewai_tools/adapters/rag_adapter.py
crewai_tools/adapters/tool_collection.py
crewai_tools/adapters/zapier_adapter.py
crewai_tools/aws/__init__.py
crewai_tools/aws/bedrock/__init__.py
crewai_tools/aws/bedrock/exceptions.py
crewai_tools/aws/bedrock/agents/README.md
crewai_tools/aws/bedrock/agents/__init__.py
crewai_tools/aws/bedrock/agents/invoke_agent_tool.py
crewai_tools/aws/bedrock/browser/README.md
crewai_tools/aws/bedrock/browser/__init__.py
crewai_tools/aws/bedrock/browser/browser_session_manager.py
crewai_tools/aws/bedrock/browser/browser_toolkit.py
crewai_tools/aws/bedrock/browser/utils.py
crewai_tools/aws/bedrock/code_interpreter/README.md
crewai_tools/aws/bedrock/code_interpreter/__init__.py
crewai_tools/aws/bedrock/code_interpreter/code_interpreter_toolkit.py
crewai_tools/aws/bedrock/knowledge_base/README.md
crewai_tools/aws/bedrock/knowledge_base/__init__.py
crewai_tools/aws/bedrock/knowledge_base/retriever_tool.py
crewai_tools/aws/s3/README.md
crewai_tools/aws/s3/__init__.py
crewai_tools/aws/s3/reader_tool.py
crewai_tools/aws/s3/writer_tool.py
crewai_tools/rag/__init__.py
crewai_tools/rag/base_loader.py
crewai_tools/rag/core.py
crewai_tools/rag/data_types.py
crewai_tools/rag/embedding_service.py
crewai_tools/rag/misc.py
crewai_tools/rag/source_content.py
crewai_tools/rag/chunkers/__init__.py
crewai_tools/rag/chunkers/base_chunker.py
crewai_tools/rag/chunkers/default_chunker.py
crewai_tools/rag/chunkers/structured_chunker.py
crewai_tools/rag/chunkers/text_chunker.py
crewai_tools/rag/chunkers/web_chunker.py
crewai_tools/rag/loaders/__init__.py
crewai_tools/rag/loaders/csv_loader.py
crewai_tools/rag/loaders/directory_loader.py
crewai_tools-1.7.1.dist-info/METADATA
crewai_tools-1.7.1.dist-info/WHEEL
crewai_tools-1.7.1.dist-info/RECORD
