Metadata-Version: 2.4
Name: crewai-tools
Version: 1.7.1
Summary: Set of tools for the crewAI framework
Project-URL: Homepage, https://crewai.com
Project-URL: Repository, https://github.com/crewAIInc/crewAI
Project-URL: Documentation, https://docs.crewai.com
Author-email: João Moura <joaomdmoura@gmail.com>
Requires-Python: <3.14,>=3.10
Requires-Dist: beautifulsoup4~=4.13.4
Requires-Dist: crewai==1.7.1
Requires-Dist: docker~=7.1.0
Requires-Dist: lancedb~=0.5.4
Requires-Dist: pymupdf~=1.26.6
Requires-Dist: python-docx~=1.2.0
Requires-Dist: pytube~=15.0.0
Requires-Dist: requests~=2.32.5
Requires-Dist: tiktoken~=0.8.0
Requires-Dist: youtube-transcript-api~=1.2.2
Provides-Extra: apify
Requires-Dist: langchain-apify<1.0.0,>=0.1.2; extra == 'apify'
Provides-Extra: beautifulsoup4
Requires-Dist: beautifulsoup4>=4.12.3; extra == 'beautifulsoup4'
Provides-Extra: bedrock
Requires-Dist: beautifulsoup4>=4.13.4; extra == 'bedrock'
Requires-Dist: bedrock-agentcore>=0.1.0; extra == 'bedrock'
Requires-Dist: nest-asyncio>=1.6.0; extra == 'bedrock'
Requires-Dist: playwright>=1.52.0; extra == 'bedrock'
Provides-Extra: browserbase
Requires-Dist: browserbase>=1.0.5; extra == 'browserbase'
Provides-Extra: composio-core
Requires-Dist: composio-core>=0.6.11.post1; extra == 'composio-core'
Provides-Extra: contextual
Requires-Dist: contextual-client>=0.1.0; extra == 'contextual'
Requires-Dist: nest-asyncio>=1.6.0; extra == 'contextual'
Provides-Extra: couchbase
Requires-Dist: couchbase>=4.3.5; extra == 'couchbase'
Provides-Extra: databricks-sdk
Requires-Dist: databricks-sdk>=0.46.0; extra == 'databricks-sdk'
Provides-Extra: exa-py
Requires-Dist: exa-py>=1.8.7; extra == 'exa-py'
Provides-Extra: firecrawl-py
Requires-Dist: firecrawl-py>=1.8.0; extra == 'firecrawl-py'
Provides-Extra: github
Requires-Dist: gitpython==3.1.38; extra == 'github'
Requires-Dist: pygithub==1.59.1; extra == 'github'
Provides-Extra: hyperbrowser
Requires-Dist: hyperbrowser>=0.18.0; extra == 'hyperbrowser'
Provides-Extra: linkup-sdk
Requires-Dist: linkup-sdk>=0.2.2; extra == 'linkup-sdk'
Provides-Extra: mcp
Requires-Dist: mcp>=1.6.0; extra == 'mcp'
Requires-Dist: mcpadapt>=0.1.9; extra == 'mcp'
Provides-Extra: mongodb
Requires-Dist: pymongo>=4.13; extra == 'mongodb'
Provides-Extra: multion
Requires-Dist: multion>=1.1.0; extra == 'multion'
Provides-Extra: mysql
Requires-Dist: pymysql>=1.1.1; extra == 'mysql'
Provides-Extra: oxylabs
Requires-Dist: oxylabs==2.0.0; extra == 'oxylabs'
Provides-Extra: patronus
Requires-Dist: patronus>=0.0.16; extra == 'patronus'
Provides-Extra: postgresql
Requires-Dist: psycopg2-binary>=2.9.10; extra == 'postgresql'
Provides-Extra: qdrant-client
Requires-Dist: qdrant-client>=1.12.1; extra == 'qdrant-client'
Provides-Extra: rag
Requires-Dist: lxml<5.4.0,>=5.3.0; extra == 'rag'
Requires-Dist: python-docx>=1.1.0; extra == 'rag'
Provides-Extra: scrapegraph-py
Requires-Dist: scrapegraph-py>=1.9.0; extra == 'scrapegraph-py'
Provides-Extra: scrapfly-sdk
Requires-Dist: scrapfly-sdk>=0.8.19; extra == 'scrapfly-sdk'
Provides-Extra: selenium
Requires-Dist: selenium>=4.27.1; extra == 'selenium'
Provides-Extra: serpapi
Requires-Dist: serpapi>=0.1.5; extra == 'serpapi'
Provides-Extra: singlestore
Requires-Dist: singlestoredb>=1.12.4; extra == 'singlestore'
Requires-Dist: sqlalchemy>=2.0.40; extra == 'singlestore'
Provides-Extra: snowflake
Requires-Dist: cryptography>=43.0.3; extra == 'snowflake'
Requires-Dist: snowflake-connector-python>=3.12.4; extra == 'snowflake'
Requires-Dist: snowflake-sqlalchemy>=1.7.3; extra == 'snowflake'
Provides-Extra: spider-client
Requires-Dist: spider-client>=0.1.25; extra == 'spider-client'
Provides-Extra: sqlalchemy
Requires-Dist: sqlalchemy>=2.0.35; extra == 'sqlalchemy'
Provides-Extra: stagehand
Requires-Dist: stagehand>=0.4.1; extra == 'stagehand'
Provides-Extra: tavily-python
Requires-Dist: tavily-python>=0.5.4; extra == 'tavily-python'
Provides-Extra: weaviate-client
Requires-Dist: weaviate-client>=4.10.2; extra == 'weaviate-client'
Provides-Extra: xml
Requires-Dist: unstructured[all-docs,local-inference]>=0.17.2; extra == 'xml'
